automated_changelog/__init__.py
automated_changelog/cli.py
automated_changelog/config.py
automated_changelog/git_state.py
automated_changelog/llm.py
automated_changelog/summarization.py
automated_changelog-0.3.0.dist-info/licenses/LICENSE
automated_changelog-0.3.0.dist-info/METADATA
automated_changelog-0.3.0.dist-info/WHEEL
automated_changelog-0.3.0.dist-info/entry_points.txt
automated_changelog-0.3.0.dist-info/top_level.txt
automated_changelog-0.3.0.dist-info/RECORD
