Metadata-Version: 2.4
Name: automated-changelog
Version: 0.3.0
Summary: LLM-powered automated changelog generation for Git repositories
Author-email: Danny Vu <danieldukevu@outlook.com>
Maintainer-email: Danny Vu <danieldukevu@outlook.com>
License-Expression: MPL-2.0
Project-URL: Homepage, https://github.com/divineunited/automated-changelog
Project-URL: Repository, https://github.com/divineunited/automated-changelog
Project-URL: Issues, https://github.com/divineunited/automated-changelog/issues
Project-URL: Changelog, https://github.com/divineunited/automated-changelog/blob/master/CHANGELOG.md
Keywords: changelog,git,automation,llm,release-notes,documentation,developer-tools
Classifier: Development Status :: 3 - Alpha
Classifier: Intended Audience :: Developers
Classifier: Operating System :: OS Independent
Classifier: Programming Language :: Python :: 3
Classifier: Programming Language :: Python :: 3.9
Classifier: Programming Language :: Python :: 3.10
Classifier: Programming Language :: Python :: 3.11
Classifier: Programming Language :: Python :: 3.12
Classifier: Topic :: Software Development :: Documentation
Classifier: Topic :: Software Development :: Version Control :: Git
Classifier: Topic :: Utilities
Classifier: Typing :: Typed
Requires-Python: >=3.9
License-File: LICENSE
Requires-Dist: click>=8.1.0
Requires-Dist: PyYAML>=6.0
Requires-Dist: litellm>=1.0.0
Requires-Dist: python-dotenv>=1.0.0
Provides-Extra: dev
Requires-Dist: pytest>=7.4.0; extra == "dev"
Requires-Dist: pytest-cov>=4.1.0; extra == "dev"
Requires-Dist: black>=23.0.0; extra == "dev"
Requires-Dist: ruff>=0.1.0; extra == "dev"
Requires-Dist: mypy>=1.0.0; extra == "dev"
Requires-Dist: build>=1.0.0; extra == "dev"
Requires-Dist: twine>=4.0.0; extra == "dev"
Dynamic: license-file
